wave_viewer/__init__.py
wave_viewer/_controller.py
wave_viewer/_viewer.py
wave_viewer-0.2.2.dist-info/LICENSE
wave_viewer-0.2.2.dist-info/METADATA
wave_viewer-0.2.2.dist-info/WHEEL
wave_viewer-0.2.2.dist-info/RECORD
