Metadata-Version: 2.1
Name: wave-viewer
Version: 0.2.2
Summary: A simple GUI for viewing waveforms.
Home-page: https://github.com/kahojyun/wave-viewer
License: MIT
Author: Jiahao Yuan
Author-email: kaho0769@qq.com
Requires-Python: >=3.7,<3.12
Classifier: License :: OSI Approved :: MIT License
Classifier: Programming Language :: Python :: 3
Classifier: Programming Language :: Python :: 3.7
Classifier: Programming Language :: Python :: 3.8
Classifier: Programming Language :: Python :: 3.9
Classifier: Programming Language :: Python :: 3.10
Classifier: Programming Language :: Python :: 3.11
Requires-Dist: importlib-metadata (>=1.0) ; python_version < "3.8"
Requires-Dist: pyside6 (>=6.5.0,<7.0.0)
Requires-Dist: vispy (>=0.13.0,<0.14.0)
Project-URL: Repository, https://github.com/kahojyun/wave-viewer
